absfuyuEX/__init__.py
absfuyuEX/__main__.py
absfuyuEX/lunar.py
absfuyuEX/temp.py
absfuyuEX/version.py
absfuyuEX/pkg_data/__init__.py
absfuyuEX/pkg_data/perfect_num_35.dat
absfuyuEX/tool/WGS.py
absfuyuEX/tool/__init__.py
absfuyuEX/tool/basic_lunar_calendar.py
absfuyuEX/tool/color_extract.py
absfuyuEX/tool/keygen.py
absfuyuEX-2.3.1.dist-info/LICENSE
absfuyuEX-2.3.1.dist-info/METADATA
absfuyuEX-2.3.1.dist-info/WHEEL
absfuyuEX-2.3.1.dist-info/entry_points.txt
absfuyuEX-2.3.1.dist-info/top_level.txt
absfuyuEX-2.3.1.dist-info/RECORD
