Metadata-Version: 2.1
Name: absfuyuEX
Version: 2.3.1
Summary: A dlc for absfuyu
Home-page: https://github.com/AbsoluteWinter/absfuyu-extra
Author: somewhatcold (AbsoluteWinter)
Author-email: this.is.a.fake.mail@fakemail.absfuyu.com
Maintainer: somewhatcold (AbsoluteWinter)
Maintainer-email: this.is.a.fake.mail@fakemail.absfuyu.com
License: MIT
Project-URL: Documentation, https://github.com/AbsoluteWinter/absfuyu-extra
Project-URL: Changes, https://github.com/AbsoluteWinter/absfuyu-extra
Project-URL: Source Code, https://github.com/AbsoluteWinter/absfuyu-extra
Project-URL: Issue Tracker, https://github.com/AbsoluteWinter/absfuyu-extra/issues
Platform: UNKNOWN
Classifier: Programming Language :: Python :: 3
Classifier: Programming Language :: Python :: 3.7
Classifier: License :: OSI Approved :: MIT License
Classifier: Operating System :: OS Independent
Classifier: Development Status :: 3 - Alpha
Classifier: Natural Language :: English
Requires-Python: <4,>=3.7
License-File: LICENSE
Requires-Dist: absfuyu[cli]
Requires-Dist: typing-extensions (>=3.7.4) ; python_version == "3.7"
